{"Chapters":[],"Artists":[],"AlbumArtists":[],"Studios":[],"Genres":[],"People":[],"ProviderIds":{},"Protocol":"Http","Path":"http://172.26.0.2:8096/LiveTv/LiveStreamFiles/76c50ce0c2ac4277bbad5231909fe42a/stream.ts","Type":"Default","Container":"mpegts","IsRemote":false,"ReadAtNativeFramerate":false,"IgnoreDts":false,"IgnoreIndex":false,"GenPtsInput":false,"SupportsTranscoding":true,"SupportsDirectStream":true,"SupportsDirectPlay":true,"IsInfiniteStream":false,"RequiresOpening":false,"RequiresClosing":false,"RequiresLooping":false,"SupportsProbing":true,"MediaStreams":[{"Codec":"hevc","ColorRange":"tv","TimeBase":"1/90000","VideoRange":"SDR","VideoRangeType":"SDR","DisplayTitle":"720p HEVC SDR","IsInterlaced":false,"BitDepth":8,"RefFrames":1,"IsDefault":false,"IsForced":false,"Height":720,"Width":1280,"AverageFrameRate":30,"RealFrameRate":29.97003,"Profile":"Main","Type":"Video","AspectRatio":"16:9","Index":0,"IsExternal":false,"IsTextSubtitleStream":false,"SupportsExternalStream":false,"PixelFormat":"yuv420p","Level":93,"IsAnamorphic":false},{"Codec":"aac","Language":"por","TimeBase":"1/90000","DisplayTitle":"Portuguese - AAC - Stereo","IsInterlaced":false,"ChannelLayout":"stereo","BitRate":96394,"Channels":2,"SampleRate":44100,"IsDefault":false,"IsForced":false,"Profile":"LC","Type":"Audio","Index":1,"IsExternal":false,"IsTextSubtitleStream":false,"SupportsExternalStream":false,"Level":0},{"Codec":"dvbsub","Language":"por","TimeBase":"1/90000","LocalizedUndefined":"Indefinido","LocalizedDefault":"Padr\u00E3o","LocalizedForced":"For\u00E7ado","LocalizedExternal":"Externo","DisplayTitle":"Portuguese - DVBSUB","IsInterlaced":false,"IsDefault":false,"IsForced":false,"Type":"Subtitle","Index":2,"IsExternal":false,"IsTextSubtitleStream":false,"SupportsExternalStream":false,"Level":0}],"MediaAttachments":[],"Formats":[],"Bitrate":96394,"RequiredHttpHeaders":{}}